pyospackage/__init__.py
pyospackage/_version.py
pyospackage/add_numbers.py
pyospackage-0.5.dist-info/METADATA
pyospackage-0.5.dist-info/WHEEL
pyospackage-0.5.dist-info/licenses/LICENSE
pyospackage-0.5.dist-info/RECORD
