Metadata-Version: 2.4
Name: pyospackage
Version: 0.5
Summary: A package that adds numbers together.
Project-URL: Homepage, https://github.com/pyopensci/pyospackage
Project-URL: Source Code, https://github.com/pyopensci/pyospackage
Project-URL: Bug Tracker, https://github.com/pyopensci/pyospackage/issues
Project-URL: Documentation, https://pyospackage.readthedocs.io
Project-URL: Download, https://pypi.org/project/pyospackage/#files
Author-email: Leah Wasser <leah@pyopensci.org>
License-Expression: MIT
License-File: LICENSE
Keywords: packaging
Classifier: Development Status :: 2 - Pre-Alpha
Classifier: Intended Audience :: Science/Research
Classifier: License :: OSI Approved :: MIT License
Classifier: Operating System :: OS Independent
Classifier: Programming Language :: Python :: 3 :: Only
Classifier: Typing :: Typed
Requires-Python: >=3.11
Requires-Dist: numpy>=2.2.6
Requires-Dist: requests>=2.32.5
Provides-Extra: dev
Requires-Dist: pre-commit; extra == 'dev'
Requires-Dist: ruff>=0.14.3; extra == 'dev'
Provides-Extra: docs
Requires-Dist: myst-parser>=4.0.1; extra == 'docs'
Requires-Dist: pydata-sphinx-theme~=0.16; extra == 'docs'
Requires-Dist: sphinx-autoapi>=3.6.0; extra == 'docs'
Requires-Dist: sphinx-autobuild>=2024.10.3; extra == 'docs'
Requires-Dist: sphinx-copybutton>=0.5.2; extra == 'docs'
Requires-Dist: sphinx-design>=0.6.1; extra == 'docs'
Requires-Dist: sphinx>=8.2.3; extra == 'docs'
Provides-Extra: tests
Requires-Dist: pytest>=8.4.2; extra == 'tests'
